perexchange/__init__.py
perexchange/core.py
perexchange/models.py
perexchange/scrapers/__init__.py
perexchange/scrapers/base.py
perexchange/scrapers/cambiafx.py
perexchange/scrapers/cambioseguro.py
perexchange/scrapers/chapacambio.py
perexchange/scrapers/cuantoestaeldolar.py
perexchange/scrapers/dollarhouse.py
perexchange/scrapers/instakash.py
perexchange/scrapers/srcambio.py
perexchange/scrapers/tkambio.py
perexchange/scrapers/tucambista.py
perexchange/scrapers/westernunion.py
perexchange/scrapers/yanki.py
perexchange-1.0.0.dist-info/METADATA
perexchange-1.0.0.dist-info/WHEEL
perexchange-1.0.0.dist-info/top_level.txt
perexchange-1.0.0.dist-info/RECORD
