Metadata-Version: 2.4
Name: perexchange
Version: 1.0.0
Summary: Library for fetching Peruvian exchange rates
Author-email: David Duran <dadch1404@gmail.com>
License-Expression: MIT
Requires-Python: >=3.9
Requires-Dist: beautifulsoup4>=4.14.2
Requires-Dist: httpx[http2]>=0.27.2
Requires-Dist: lxml>=6.0.2
